latex2readme.py
latex2readme-0.0.2.dist-info/LICENSE.txt
latex2readme-0.0.2.dist-info/METADATA
latex2readme-0.0.2.dist-info/WHEEL
latex2readme-0.0.2.dist-info/entry_points.txt
latex2readme-0.0.2.dist-info/top_level.txt
latex2readme-0.0.2.dist-info/RECORD
