Metadata-Version: 2.1
Name: latex2readme
Version: 0.0.2
Summary: Convert LaTeX documents to README.md files
Home-page: https://github.com/leon-h-a/latex2readme
License: MIT
License-File: LICENSE.txt
Requires-Dist: natsort (==8.4.0)
Requires-Dist: pdf2image (==1.16.3)
Requires-Dist: pillow (==10.2.0)
Requires-Dist: pdflatex
